{
  "updated": "14 Jul 2026, 09:49 UTC",
  "updatedEpoch": 1784022551205,
  "results": [
    {
      "gw": 1,
      "stage": "group",
      "home": "Argentina",
      "homeScore": 3,
      "away": "Algeria",
      "awayScore": 0
    },
    {
      "gw": 1,
      "stage": "group",
      "home": "Australia",
      "homeScore": 2,
      "away": "Turkey",
      "awayScore": 0
    },
    {
      "gw": 1,
      "stage": "group",
      "home": "Austria",
      "homeScore": 3,
      "away": "Jordan",
      "awayScore": 1
    },
    {
      "gw": 1,
      "stage": "group",
      "home": "Belgium",
      "homeScore": 1,
      "away": "Egypt",
      "awayScore": 1
    },
    {
      "gw": 1,
      "stage": "group",
      "home": "Brazil",
      "homeScore": 1,
      "away": "Morocco",
      "awayScore": 1
    },
    {
      "gw": 1,
      "stage": "group",
      "home": "Canada",
      "homeScore": 1,
      "away": "Bosnia & H.",
      "awayScore": 1
    },
    {
      "gw": 1,
      "stage": "group",
      "home": "England",
      "homeScore": 4,
      "away": "Croatia",
      "awayScore": 2
    },
    {
      "gw": 1,
      "stage": "group",
      "home": "France",
      "homeScore": 3,
      "away": "Senegal",
      "awayScore": 1
    },
    {
      "gw": 1,
      "stage": "group",
      "home": "Germany",
      "homeScore": 7,
      "away": "Curaçao",
      "awayScore": 1
    },
    {
      "gw": 1,
      "stage": "group",
      "home": "Ghana",
      "homeScore": 1,
      "away": "Panama",
      "awayScore": 0
    },
    {
      "gw": 1,
      "stage": "group",
      "home": "Haiti",
      "homeScore": 0,
      "away": "Scotland",
      "awayScore": 1
    },
    {
      "gw": 1,
      "stage": "group",
      "home": "Iran",
      "homeScore": 2,
      "away": "New Zealand",
      "awayScore": 2
    },
    {
      "gw": 1,
      "stage": "group",
      "home": "Iraq",
      "homeScore": 1,
      "away": "Norway",
      "awayScore": 4
    },
    {
      "gw": 1,
      "stage": "group",
      "home": "Ivory Coast",
      "homeScore": 1,
      "away": "Ecuador",
      "awayScore": 0
    },
    {
      "gw": 1,
      "stage": "group",
      "home": "Mexico",
      "homeScore": 2,
      "away": "South Africa",
      "awayScore": 0
    },
    {
      "gw": 1,
      "stage": "group",
      "home": "Netherlands",
      "homeScore": 2,
      "away": "Japan",
      "awayScore": 2
    },
    {
      "gw": 1,
      "stage": "group",
      "home": "Portugal",
      "homeScore": 1,
      "away": "DR Congo",
      "awayScore": 1
    },
    {
      "gw": 1,
      "stage": "group",
      "home": "Qatar",
      "homeScore": 1,
      "away": "Switzerland",
      "awayScore": 1
    },
    {
      "gw": 1,
      "stage": "group",
      "home": "Saudi Arabia",
      "homeScore": 1,
      "away": "Uruguay",
      "awayScore": 1
    },
    {
      "gw": 1,
      "stage": "group",
      "home": "South Korea",
      "homeScore": 2,
      "away": "Czech Rep.",
      "awayScore": 1
    },
    {
      "gw": 1,
      "stage": "group",
      "home": "Spain",
      "homeScore": 0,
      "away": "Cape Verde",
      "awayScore": 0
    },
    {
      "gw": 1,
      "stage": "group",
      "home": "Sweden",
      "homeScore": 5,
      "away": "Tunisia",
      "awayScore": 1
    },
    {
      "gw": 1,
      "stage": "group",
      "home": "USA",
      "homeScore": 4,
      "away": "Paraguay",
      "awayScore": 1
    },
    {
      "gw": 1,
      "stage": "group",
      "home": "Uzbekistan",
      "homeScore": 1,
      "away": "Colombia",
      "awayScore": 3
    },
    {
      "gw": 2,
      "stage": "group",
      "home": "Argentina",
      "homeScore": 2,
      "away": "Austria",
      "awayScore": 0
    },
    {
      "gw": 2,
      "stage": "group",
      "home": "Belgium",
      "homeScore": 0,
      "away": "Iran",
      "awayScore": 0
    },
    {
      "gw": 2,
      "stage": "group",
      "home": "Brazil",
      "homeScore": 3,
      "away": "Haiti",
      "awayScore": 0
    },
    {
      "gw": 2,
      "stage": "group",
      "home": "Canada",
      "homeScore": 6,
      "away": "Qatar",
      "awayScore": 0
    },
    {
      "gw": 2,
      "stage": "group",
      "home": "Colombia",
      "homeScore": 1,
      "away": "DR Congo",
      "awayScore": 0
    },
    {
      "gw": 2,
      "stage": "group",
      "home": "Czech Rep.",
      "homeScore": 1,
      "away": "South Africa",
      "awayScore": 1
    },
    {
      "gw": 2,
      "stage": "group",
      "home": "Ecuador",
      "homeScore": 0,
      "away": "Curaçao",
      "awayScore": 0
    },
    {
      "gw": 2,
      "stage": "group",
      "home": "England",
      "homeScore": 0,
      "away": "Ghana",
      "awayScore": 0
    },
    {
      "gw": 2,
      "stage": "group",
      "home": "France",
      "homeScore": 3,
      "away": "Iraq",
      "awayScore": 0
    },
    {
      "gw": 2,
      "stage": "group",
      "home": "Germany",
      "homeScore": 2,
      "away": "Ivory Coast",
      "awayScore": 1
    },
    {
      "gw": 2,
      "stage": "group",
      "home": "Jordan",
      "homeScore": 1,
      "away": "Algeria",
      "awayScore": 2
    },
    {
      "gw": 2,
      "stage": "group",
      "home": "Mexico",
      "homeScore": 1,
      "away": "South Korea",
      "awayScore": 0
    },
    {
      "gw": 2,
      "stage": "group",
      "home": "Netherlands",
      "homeScore": 5,
      "away": "Sweden",
      "awayScore": 1
    },
    {
      "gw": 2,
      "stage": "group",
      "home": "New Zealand",
      "homeScore": 1,
      "away": "Egypt",
      "awayScore": 3
    },
    {
      "gw": 2,
      "stage": "group",
      "home": "Norway",
      "homeScore": 3,
      "away": "Senegal",
      "awayScore": 2
    },
    {
      "gw": 2,
      "stage": "group",
      "home": "Panama",
      "homeScore": 0,
      "away": "Croatia",
      "awayScore": 1
    },
    {
      "gw": 2,
      "stage": "group",
      "home": "Portugal",
      "homeScore": 5,
      "away": "Uzbekistan",
      "awayScore": 0
    },
    {
      "gw": 2,
      "stage": "group",
      "home": "Scotland",
      "homeScore": 0,
      "away": "Morocco",
      "awayScore": 1
    },
    {
      "gw": 2,
      "stage": "group",
      "home": "Spain",
      "homeScore": 4,
      "away": "Saudi Arabia",
      "awayScore": 0
    },
    {
      "gw": 2,
      "stage": "group",
      "home": "Switzerland",
      "homeScore": 4,
      "away": "Bosnia & H.",
      "awayScore": 1
    },
    {
      "gw": 2,
      "stage": "group",
      "home": "Tunisia",
      "homeScore": 0,
      "away": "Japan",
      "awayScore": 4
    },
    {
      "gw": 2,
      "stage": "group",
      "home": "Turkey",
      "homeScore": 0,
      "away": "Paraguay",
      "awayScore": 1
    },
    {
      "gw": 2,
      "stage": "group",
      "home": "Uruguay",
      "homeScore": 2,
      "away": "Cape Verde",
      "awayScore": 2
    },
    {
      "gw": 2,
      "stage": "group",
      "home": "USA",
      "homeScore": 2,
      "away": "Australia",
      "awayScore": 0
    },
    {
      "gw": 3,
      "stage": "group",
      "home": "Algeria",
      "homeScore": 3,
      "away": "Austria",
      "awayScore": 3
    },
    {
      "gw": 3,
      "stage": "group",
      "home": "Bosnia & H.",
      "homeScore": 3,
      "away": "Qatar",
      "awayScore": 1
    },
    {
      "gw": 3,
      "stage": "group",
      "home": "Cape Verde",
      "homeScore": 0,
      "away": "Saudi Arabia",
      "awayScore": 0
    },
    {
      "gw": 3,
      "stage": "group",
      "home": "Colombia",
      "homeScore": 0,
      "away": "Portugal",
      "awayScore": 0
    },
    {
      "gw": 3,
      "stage": "group",
      "home": "Croatia",
      "homeScore": 2,
      "away": "Ghana",
      "awayScore": 1
    },
    {
      "gw": 3,
      "stage": "group",
      "home": "Curaçao",
      "homeScore": 0,
      "away": "Ivory Coast",
      "awayScore": 2
    },
    {
      "gw": 3,
      "stage": "group",
      "home": "Czech Rep.",
      "homeScore": 0,
      "away": "Mexico",
      "awayScore": 3
    },
    {
      "gw": 3,
      "stage": "group",
      "home": "DR Congo",
      "homeScore": 3,
      "away": "Uzbekistan",
      "awayScore": 1
    },
    {
      "gw": 3,
      "stage": "group",
      "home": "Ecuador",
      "homeScore": 2,
      "away": "Germany",
      "awayScore": 1
    },
    {
      "gw": 3,
      "stage": "group",
      "home": "Egypt",
      "homeScore": 1,
      "away": "Iran",
      "awayScore": 1
    },
    {
      "gw": 3,
      "stage": "group",
      "home": "Japan",
      "homeScore": 1,
      "away": "Sweden",
      "awayScore": 1
    },
    {
      "gw": 3,
      "stage": "group",
      "home": "Jordan",
      "homeScore": 1,
      "away": "Argentina",
      "awayScore": 3
    },
    {
      "gw": 3,
      "stage": "group",
      "home": "Morocco",
      "homeScore": 4,
      "away": "Haiti",
      "awayScore": 2
    },
    {
      "gw": 3,
      "stage": "group",
      "home": "New Zealand",
      "homeScore": 1,
      "away": "Belgium",
      "awayScore": 5
    },
    {
      "gw": 3,
      "stage": "group",
      "home": "Norway",
      "homeScore": 1,
      "away": "France",
      "awayScore": 4
    },
    {
      "gw": 3,
      "stage": "group",
      "home": "Panama",
      "homeScore": 0,
      "away": "England",
      "awayScore": 2
    },
    {
      "gw": 3,
      "stage": "group",
      "home": "Paraguay",
      "homeScore": 0,
      "away": "Australia",
      "awayScore": 0
    },
    {
      "gw": 3,
      "stage": "group",
      "home": "Scotland",
      "homeScore": 0,
      "away": "Brazil",
      "awayScore": 3
    },
    {
      "gw": 3,
      "stage": "group",
      "home": "Senegal",
      "homeScore": 5,
      "away": "Iraq",
      "awayScore": 0
    },
    {
      "gw": 3,
      "stage": "group",
      "home": "South Africa",
      "homeScore": 1,
      "away": "South Korea",
      "awayScore": 0
    },
    {
      "gw": 3,
      "stage": "group",
      "home": "Switzerland",
      "homeScore": 2,
      "away": "Canada",
      "awayScore": 1
    },
    {
      "gw": 3,
      "stage": "group",
      "home": "Tunisia",
      "homeScore": 1,
      "away": "Netherlands",
      "awayScore": 3
    },
    {
      "gw": 3,
      "stage": "group",
      "home": "Turkey",
      "homeScore": 3,
      "away": "USA",
      "awayScore": 2
    },
    {
      "gw": 3,
      "stage": "group",
      "home": "Uruguay",
      "homeScore": 0,
      "away": "Spain",
      "awayScore": 1
    },
    {
      "gw": 4,
      "stage": "r32",
      "home": "Argentina",
      "homeScore": 3,
      "away": "Cape Verde",
      "awayScore": 2
    },
    {
      "gw": 4,
      "stage": "r32",
      "home": "Australia",
      "homeScore": 3,
      "away": "Egypt",
      "awayScore": 5
    },
    {
      "gw": 4,
      "stage": "r32",
      "home": "Belgium",
      "homeScore": 3,
      "away": "Senegal",
      "awayScore": 2
    },
    {
      "gw": 4,
      "stage": "r32",
      "home": "Brazil",
      "homeScore": 2,
      "away": "Japan",
      "awayScore": 1
    },
    {
      "gw": 4,
      "stage": "r32",
      "home": "Colombia",
      "homeScore": 1,
      "away": "Ghana",
      "awayScore": 0
    },
    {
      "gw": 4,
      "stage": "r32",
      "home": "England",
      "homeScore": 2,
      "away": "DR Congo",
      "awayScore": 1
    },
    {
      "gw": 4,
      "stage": "r32",
      "home": "France",
      "homeScore": 3,
      "away": "Sweden",
      "awayScore": 0
    },
    {
      "gw": 4,
      "stage": "r32",
      "home": "Germany",
      "homeScore": 4,
      "away": "Paraguay",
      "awayScore": 5
    },
    {
      "gw": 4,
      "stage": "r32",
      "home": "Ivory Coast",
      "homeScore": 1,
      "away": "Norway",
      "awayScore": 2
    },
    {
      "gw": 4,
      "stage": "r32",
      "home": "Mexico",
      "homeScore": 2,
      "away": "Ecuador",
      "awayScore": 0
    },
    {
      "gw": 4,
      "stage": "r32",
      "home": "Netherlands",
      "homeScore": 3,
      "away": "Morocco",
      "awayScore": 4
    },
    {
      "gw": 4,
      "stage": "r32",
      "home": "Portugal",
      "homeScore": 2,
      "away": "Croatia",
      "awayScore": 1
    },
    {
      "gw": 4,
      "stage": "r32",
      "home": "South Africa",
      "homeScore": 0,
      "away": "Canada",
      "awayScore": 1
    },
    {
      "gw": 4,
      "stage": "r32",
      "home": "Spain",
      "homeScore": 3,
      "away": "Austria",
      "awayScore": 0
    },
    {
      "gw": 4,
      "stage": "r32",
      "home": "Switzerland",
      "homeScore": 2,
      "away": "Algeria",
      "awayScore": 0
    },
    {
      "gw": 4,
      "stage": "r32",
      "home": "USA",
      "homeScore": 2,
      "away": "Bosnia & H.",
      "awayScore": 0
    },
    {
      "gw": 5,
      "stage": "r16",
      "home": "Argentina",
      "homeScore": 3,
      "away": "Egypt",
      "awayScore": 2
    },
    {
      "gw": 5,
      "stage": "r16",
      "home": "Brazil",
      "homeScore": 1,
      "away": "Norway",
      "awayScore": 2
    },
    {
      "gw": 5,
      "stage": "r16",
      "home": "Canada",
      "homeScore": 0,
      "away": "Morocco",
      "awayScore": 3
    },
    {
      "gw": 5,
      "stage": "r16",
      "home": "Mexico",
      "homeScore": 2,
      "away": "England",
      "awayScore": 3
    },
    {
      "gw": 5,
      "stage": "r16",
      "home": "Paraguay",
      "homeScore": 0,
      "away": "France",
      "awayScore": 1
    },
    {
      "gw": 5,
      "stage": "r16",
      "home": "Portugal",
      "homeScore": 0,
      "away": "Spain",
      "awayScore": 1
    },
    {
      "gw": 5,
      "stage": "r16",
      "home": "Switzerland",
      "homeScore": 4,
      "away": "Colombia",
      "awayScore": 3
    },
    {
      "gw": 5,
      "stage": "r16",
      "home": "USA",
      "homeScore": 1,
      "away": "Belgium",
      "awayScore": 4
    },
    {
      "gw": 6,
      "stage": "qf",
      "home": "Argentina",
      "homeScore": 3,
      "away": "Switzerland",
      "awayScore": 1
    },
    {
      "gw": 6,
      "stage": "qf",
      "home": "France",
      "homeScore": 2,
      "away": "Morocco",
      "awayScore": 0
    },
    {
      "gw": 6,
      "stage": "qf",
      "home": "Norway",
      "homeScore": 1,
      "away": "England",
      "awayScore": 2
    },
    {
      "gw": 6,
      "stage": "qf",
      "home": "Spain",
      "homeScore": 2,
      "away": "Belgium",
      "awayScore": 1
    }
  ],
  "groupFinishes": [
    {
      "country": "Algeria",
      "finish": 3
    },
    {
      "country": "Argentina",
      "finish": 1
    },
    {
      "country": "Australia",
      "finish": 2
    },
    {
      "country": "Austria",
      "finish": 2
    },
    {
      "country": "Belgium",
      "finish": 1
    },
    {
      "country": "Bosnia & H.",
      "finish": 3
    },
    {
      "country": "Brazil",
      "finish": 1
    },
    {
      "country": "Canada",
      "finish": 2
    },
    {
      "country": "Cape Verde",
      "finish": 2
    },
    {
      "country": "Colombia",
      "finish": 1
    },
    {
      "country": "Croatia",
      "finish": 2
    },
    {
      "country": "Curaçao",
      "finish": 4
    },
    {
      "country": "Czech Rep.",
      "finish": 4
    },
    {
      "country": "DR Congo",
      "finish": 3
    },
    {
      "country": "Ecuador",
      "finish": 3
    },
    {
      "country": "Egypt",
      "finish": 2
    },
    {
      "country": "England",
      "finish": 1
    },
    {
      "country": "France",
      "finish": 1
    },
    {
      "country": "Germany",
      "finish": 1
    },
    {
      "country": "Ghana",
      "finish": 3
    },
    {
      "country": "Haiti",
      "finish": 4
    },
    {
      "country": "Iran",
      "finish": 3
    },
    {
      "country": "Iraq",
      "finish": 4
    },
    {
      "country": "Ivory Coast",
      "finish": 2
    },
    {
      "country": "Japan",
      "finish": 2
    },
    {
      "country": "Jordan",
      "finish": 4
    },
    {
      "country": "Mexico",
      "finish": 1
    },
    {
      "country": "Morocco",
      "finish": 2
    },
    {
      "country": "Netherlands",
      "finish": 1
    },
    {
      "country": "New Zealand",
      "finish": 4
    },
    {
      "country": "Norway",
      "finish": 2
    },
    {
      "country": "Panama",
      "finish": 4
    },
    {
      "country": "Paraguay",
      "finish": 3
    },
    {
      "country": "Portugal",
      "finish": 2
    },
    {
      "country": "Qatar",
      "finish": 4
    },
    {
      "country": "Saudi Arabia",
      "finish": 4
    },
    {
      "country": "Scotland",
      "finish": 3
    },
    {
      "country": "Senegal",
      "finish": 3
    },
    {
      "country": "South Africa",
      "finish": 2
    },
    {
      "country": "South Korea",
      "finish": 3
    },
    {
      "country": "Spain",
      "finish": 1
    },
    {
      "country": "Sweden",
      "finish": 3
    },
    {
      "country": "Switzerland",
      "finish": 1
    },
    {
      "country": "Tunisia",
      "finish": 4
    },
    {
      "country": "Turkey",
      "finish": 4
    },
    {
      "country": "Uruguay",
      "finish": 3
    },
    {
      "country": "USA",
      "finish": 1
    },
    {
      "country": "Uzbekistan",
      "finish": 4
    }
  ],
  "exits": [
    {
      "country": "Algeria",
      "stage": "r32"
    },
    {
      "country": "Australia",
      "stage": "r32"
    },
    {
      "country": "Austria",
      "stage": "r32"
    },
    {
      "country": "Belgium",
      "stage": "qf"
    },
    {
      "country": "Bosnia & H.",
      "stage": "r32"
    },
    {
      "country": "Brazil",
      "stage": "r16"
    },
    {
      "country": "Canada",
      "stage": "r16"
    },
    {
      "country": "Cape Verde",
      "stage": "r32"
    },
    {
      "country": "Colombia",
      "stage": "r16"
    },
    {
      "country": "Croatia",
      "stage": "r32"
    },
    {
      "country": "DR Congo",
      "stage": "r32"
    },
    {
      "country": "Ecuador",
      "stage": "r32"
    },
    {
      "country": "Egypt",
      "stage": "r16"
    },
    {
      "country": "Germany",
      "stage": "r32"
    },
    {
      "country": "Ghana",
      "stage": "r32"
    },
    {
      "country": "Ivory Coast",
      "stage": "r32"
    },
    {
      "country": "Japan",
      "stage": "r32"
    },
    {
      "country": "Mexico",
      "stage": "r16"
    },
    {
      "country": "Morocco",
      "stage": "qf"
    },
    {
      "country": "Netherlands",
      "stage": "r32"
    },
    {
      "country": "Norway",
      "stage": "qf"
    },
    {
      "country": "Paraguay",
      "stage": "r16"
    },
    {
      "country": "Portugal",
      "stage": "r16"
    },
    {
      "country": "Senegal",
      "stage": "r32"
    },
    {
      "country": "South Africa",
      "stage": "r32"
    },
    {
      "country": "Sweden",
      "stage": "r32"
    },
    {
      "country": "Switzerland",
      "stage": "qf"
    },
    {
      "country": "USA",
      "stage": "r16"
    }
  ],
  "eliminated": [
    "Algeria",
    "Australia",
    "Austria",
    "Belgium",
    "Bosnia & H.",
    "Brazil",
    "Canada",
    "Cape Verde",
    "Colombia",
    "Croatia",
    "Curaçao",
    "Czech Rep.",
    "DR Congo",
    "Ecuador",
    "Egypt",
    "Germany",
    "Ghana",
    "Haiti",
    "Iran",
    "Iraq",
    "Ivory Coast",
    "Japan",
    "Jordan",
    "Mexico",
    "Morocco",
    "Netherlands",
    "New Zealand",
    "Norway",
    "Panama",
    "Paraguay",
    "Portugal",
    "Qatar",
    "Saudi Arabia",
    "Scotland",
    "Senegal",
    "South Africa",
    "South Korea",
    "Sweden",
    "Switzerland",
    "Tunisia",
    "Turkey",
    "USA",
    "Uruguay",
    "Uzbekistan"
  ],
  "fixtures": [
    {
      "stage": "sf",
      "home": "France",
      "away": "Spain",
      "utcDate": "2026-07-14T19:00:00Z"
    },
    {
      "stage": "sf",
      "home": "England",
      "away": "Argentina",
      "utcDate": "2026-07-15T19:00:00Z"
    }
  ]
}
